MANIFEST.in
README.md
package_requirements.txt
setup.py
easy_thumbnails_admin/__init__.py
easy_thumbnails_admin/_version.py
easy_thumbnails_admin/admin.py
easy_thumbnails_admin/apps.py
easy_thumbnails_admin/cache.py
easy_thumbnails_admin/files.py
easy_thumbnails_admin/models.py
easy_thumbnails_admin/monkey_patch.py
easy_thumbnails_admin/namers.py
easy_thumbnails_admin/options.py
easy_thumbnails_admin/processors.py
easy_thumbnails_admin/settings.py
easy_thumbnails_admin/urls.py
easy_thumbnails_admin/views.py
easy_thumbnails_admin/widgets.py
easy_thumbnails_admin.egg-info/PKG-INFO
easy_thumbnails_admin.egg-info/SOURCES.txt
easy_thumbnails_admin.egg-info/dependency_links.txt
easy_thumbnails_admin.egg-info/not-zip-safe
easy_thumbnails_admin.egg-info/requires.txt
easy_thumbnails_admin.egg-info/top_level.txt
easy_thumbnails_admin/migrations/0001_initial.py
easy_thumbnails_admin/migrations/__init__.py
easy_thumbnails_admin/templatetags/__init__.py
easy_thumbnails_admin/templatetags/easy_thumbnail_admin.py
easy_thumbnails_admin/utils/__init__.py
easy_thumbnails_admin/utils/json.py
easy_thumbnails_admin/utils/preview.py
easy_thumbnails_admin/utils/queryset.py