Metadata-Version: 1.1
Name: easy-thumbnails-admin
Version: 0.0.3
Summary: Admin interface for editing thumbnail aliases
Home-page: https://github.com/Apkawa/easy-thumbnails-admin'
Author: Apkawa
Author-email: apkawa@gmail.com
License: UNKNOWN
Keywords: django,admin,easy-thumbnails
Platform: UNKNOWN
Classifier: Development Status :: 3 - Alpha
Classifier: Framework :: Django
Classifier: Framework :: Django :: 1.8
Classifier: Framework :: Django :: 1.9
Classifier: Framework :: Django :: 1.10
Classifier: Framework :: Django :: 1.11
Classifier: Intended Audience :: Developers
Classifier: License :: OSI Approved :: MIT License
Classifier: Programming Language :: Python
Classifier: Programming Language :: Python :: 2.7
Classifier: Programming Language :: Python :: 3.4
Classifier: Programming Language :: Python :: 3.5
Classifier: Programming Language :: Python :: 3.6
